Metadata-Version: 1.1
Name: edb
Version: 0.0.2
Summary: Core EdgeDB Namespace
Home-page: https://github.com/edgedb/edgedb
Author: MagicStack Inc
Author-email: hello@magic.io
License: Apache License, Version 2.0
Platform: UNKNOWN
Classifier: License :: OSI Approved :: Apache Software License
Classifier: Intended Audience :: Developers
Classifier: Programming Language :: Python :: 3 :: Only
Classifier: Operating System :: POSIX
Classifier: Operating System :: MacOS :: MacOS X
Classifier: Operating System :: Microsoft :: Windows
Provides: edb
